LICENSE
MANIFEST.in
README.md
setup.cfg
setup.py
gcamreader/__init__.py
gcamreader/__main__.py
gcamreader/cli.py
gcamreader/querymi.py
gcamreader.egg-info/PKG-INFO
gcamreader.egg-info/SOURCES.txt
gcamreader.egg-info/dependency_links.txt
gcamreader.egg-info/entry_points.txt
gcamreader.egg-info/not-zip-safe
gcamreader.egg-info/requires.txt
gcamreader.egg-info/top_level.txt
gcamreader/ModelInterface/Main_queries.xml
gcamreader/ModelInterface/ModelInterface.jar
gcamreader/ModelInterface/batch-prototype.xml
gcamreader/ModelInterface/batch-sample.xml
gcamreader/ModelInterface/model_interface.properties
gcamreader/ModelInterface/sample-queries-interactive.xml
gcamreader/ModelInterface/sample-queries.xml
gcamreader/ModelInterface/sample.csv
gcamreader/ModelInterface/sample_with_errors.csv
gcamreader/ModelInterface/jars/BaseX-9.5.0.jar
gcamreader/tests/__init__.py
gcamreader/tests/test_querymi.py
gcamreader/tests/data/comp_outputs/land_query.csv
gcamreader/tests/data/queries/query_land_reg32_basin235_gcam5p0.xml
gcamreader/tests/data/sample_basexdb/atv.basex
gcamreader/tests/data/sample_basexdb/inf.basex
gcamreader/tests/data/sample_basexdb/tbl.basex
gcamreader/tests/data/sample_basexdb/tbli.basex
gcamreader/tests/data/sample_basexdb/txt.basex
gcamreader/tests/data/sample_basexdb/txtl.basex
gcamreader/tests/data/sample_basexdb/txtr.basex