Metadata-Version: 2.1
Name: gcamreader
Version: 1.4.0
Summary: Tools for importing GCAM output data
Home-page: https://github.com/JGCRI/gcamreader
Author: Robert Link
Author-email: robert.link@pnnl.gov
License: BSD 2-Clause
Requires-Python: >=3.9
License-File: LICENSE
